setup.cfg
setup.py
topsis_kamakshi/__init__.py
topsis_kamakshi/topsis_code.py
topsis_kamakshi/topsis_kamakshi.py
topsis_kamakshi.egg-info/PKG-INFO
topsis_kamakshi.egg-info/SOURCES.txt
topsis_kamakshi.egg-info/dependency_links.txt
topsis_kamakshi.egg-info/top_level.txt